cyqnt_trd/__init__.py
cyqnt_trd/diagnose_api.py
cyqnt_trd/test.py
cyqnt_trd/backtesting/README.md
cyqnt_trd/backtesting/__init__.py
cyqnt_trd/backtesting/factor_test.py
cyqnt_trd/backtesting/framework.py
cyqnt_trd/backtesting/strategy_backtest.py
cyqnt_trd/get_data/__init__.py
cyqnt_trd/get_data/get_futures_data.py
cyqnt_trd/get_data/get_kline_with_factor.py
cyqnt_trd/get_data/get_trending_data.py
cyqnt_trd/get_data/get_web3_trending_data.py
cyqnt_trd/online_trading/__init__.py
cyqnt_trd/online_trading/realtime_price_tracker.py
cyqnt_trd/test_script/README.md
cyqnt_trd/test_script/get_network_info.py
cyqnt_trd/test_script/realtime_price_tracker.py
cyqnt_trd/test_script/test_order.py
cyqnt_trd/trading_signal/README.md
cyqnt_trd/trading_signal/__init__.py
cyqnt_trd/trading_signal/example_test_alpha.py
cyqnt_trd/trading_signal/example_usage.py
cyqnt_trd/trading_signal/factor_details.json
cyqnt_trd/trading_signal/factor/__init__.py
cyqnt_trd/trading_signal/factor/adx_factor.py
cyqnt_trd/trading_signal/factor/ao_factor.py
cyqnt_trd/trading_signal/factor/bbp_factor.py
cyqnt_trd/trading_signal/factor/cci_factor.py
cyqnt_trd/trading_signal/factor/ema_factor.py
cyqnt_trd/trading_signal/factor/ma_factor.py
cyqnt_trd/trading_signal/factor/macd_factor.py
cyqnt_trd/trading_signal/factor/momentum_factor.py
cyqnt_trd/trading_signal/factor/rsi_factor.py
cyqnt_trd/trading_signal/factor/stochastic_factor.py
cyqnt_trd/trading_signal/factor/stochastic_tsi_factor.py
cyqnt_trd/trading_signal/factor/uo_factor.py
cyqnt_trd/trading_signal/factor/williams_r_factor.py
cyqnt_trd/trading_signal/selected_alpha/__init__.py
cyqnt_trd/trading_signal/selected_alpha/alpha1.py
cyqnt_trd/trading_signal/selected_alpha/alpha10.py
cyqnt_trd/trading_signal/selected_alpha/alpha100.py
cyqnt_trd/trading_signal/selected_alpha/alpha101.py
cyqnt_trd/trading_signal/selected_alpha/alpha11.py
cyqnt_trd/trading_signal/selected_alpha/alpha12.py
cyqnt_trd/trading_signal/selected_alpha/alpha13.py
cyqnt_trd-0.1.6.dist-info/licenses/LICENSE
cyqnt_trd-0.1.6.dist-info/METADATA
cyqnt_trd-0.1.6.dist-info/WHEEL
cyqnt_trd-0.1.6.dist-info/top_level.txt
cyqnt_trd-0.1.6.dist-info/RECORD
