Metadata-Version: 2.4
Name: cyqnt-trd
Version: 0.1.6
Summary: A cryptocurrency trading toolkit with data fetching, signal generation, and backtesting capabilities
Author-email: Haowen Wang <wanghw@zju.edu.cn>
License-Expression: MIT
Project-URL: Homepage, https://github.com/whw199833/cyqnt_trd
Project-URL: Repository, https://github.com/whw199833/cyqnt_trd
Project-URL: Issues, https://github.com/whw199833/cyqnt_trd/issues
Classifier: Development Status :: 3 - Alpha
Classifier: Intended Audience :: Developers
Classifier: Intended Audience :: Financial and Insurance Industry
Classifier: Programming Language :: Python :: 3
Classifier: Programming Language :: Python :: 3.8
Classifier: Programming Language :: Python :: 3.9
Classifier: Programming Language :: Python :: 3.10
Classifier: Topic :: Office/Business :: Financial :: Investment
Requires-Python: <3.11,>=3.8
License-File: LICENSE
Requires-Dist: pandas<1.6.0,>=1.5.0
Requires-Dist: numpy<1.25.0,>=1.23.0
Requires-Dist: matplotlib<3.8.0,>=3.5.0
Requires-Dist: scipy<1.11.0,>=1.9.0
Requires-Dist: requests<2.32.0,>=2.28.0
Requires-Dist: binance-sdk-spot
Requires-Dist: binance-sdk-derivatives-trading-usds-futures
Requires-Dist: binance-sdk-algo
Requires-Dist: binance-common
Provides-Extra: dev
Requires-Dist: pytest<8.0.0,>=7.0.0; extra == "dev"
Requires-Dist: pytest-cov<5.0.0,>=4.0.0; extra == "dev"
Requires-Dist: black<24.0.0,>=22.0.0; extra == "dev"
Requires-Dist: ruff<0.2.0,>=0.1.0; extra == "dev"
Dynamic: license-file
